README.rst
setup.py
testdatagen/__init__.py
testdatagen/nameandaddr.py
testdatagen.egg-info/PKG-INFO
testdatagen.egg-info/SOURCES.txt
testdatagen.egg-info/dependency_links.txt
testdatagen.egg-info/top_level.txt
testdatagen/data/testdata_dn.csv
testdatagen/data/testdata_fn.csv
testdatagen/data/testdata_ln.csv
testdatagen/data/testdata_st.csv
testdatagen/data/us_postal_codes.csv