Metadata-Version: 1.1
Name: testdatagen
Version: 0.1.19
Summary: Generates pipe delimited test data
Home-page: https://github.com/ramnemani/testdatagen
Author: Ramakrishna Nemani
Author-email: ram.nemani@gmail.com
License: MIT
Download-URL: https://github.com/ramnemani/testdatagen/archive/0.1.19.tar.gz
Keywords: testdata,test data,fake
Platform: UNKNOWN
Classifier: Development Status :: 5 - Production/Stable
Classifier: License :: OSI Approved :: MIT License
Classifier: Programming Language :: Python :: 2.7
Classifier: Programming Language :: Python :: 3.5
Classifier: Intended Audience :: Developers
Classifier: Topic :: Utilities
